zhinst/seqc_compiler/__init__.py
zhinst/seqc_compiler/__init__.pyi
zhinst/seqc_compiler/_seqc_compiler.so
zhinst/seqc_compiler/py.typed
zhinst_seqc_compiler-25.10.1.4.dist-info/METADATA
zhinst_seqc_compiler-25.10.1.4.dist-info/WHEEL
zhinst_seqc_compiler-25.10.1.4.dist-info/licenses/LICENSE.txt
zhinst_seqc_compiler-25.10.1.4.dist-info/RECORD
